swagger_api/__init__.py
swagger_api/swagger_api.py
swagger_api-1.0.0.dist-info/licenses/LICENSE
swagger_api-1.0.0.dist-info/METADATA
swagger_api-1.0.0.dist-info/WHEEL
swagger_api-1.0.0.dist-info/top_level.txt
swagger_api-1.0.0.dist-info/RECORD
