Metadata-Version: 2.4
Name: swagger_api
Version: 1.0.0
Summary: A tool to fetch and parse Swagger API definitions from a given URL.
Author: HP Inc.
License-File: LICENSE
Requires-Dist: requests>=2.25.1
Requires-Dist: mcp>=0.1.0
Dynamic: author
Dynamic: description
Dynamic: description-content-type
Dynamic: license-file
Dynamic: requires-dist
Dynamic: summary
